setup.py
api_github/__init__.py
api_github/api.py
api_github.egg-info/PKG-INFO
api_github.egg-info/SOURCES.txt
api_github.egg-info/dependency_links.txt
api_github.egg-info/requires.txt
api_github.egg-info/top_level.txt