Metadata-Version: 1.1
Name: api-github
Version: 1.0
Summary: agihub.com API Python wrapper
Home-page: https://github.com/vir-mir/github_api
Author: vir-mir
Author-email: virmir49@gmail.com
License: MIT
Keywords: github.com github api
Platform: UNKNOWN
Classifier: Environment :: Web Environment
Classifier: Intended Audience :: Developers
Classifier: License :: OSI Approved :: MIT License
Classifier: Programming Language :: Python :: 2.7
Classifier: Programming Language :: Python :: 3.3
Classifier: Programming Language :: Python :: 3.4
Classifier: Topic :: Software Development :: Libraries :: Python Modules
